pymoa_remote/__init__.py
pymoa_remote/_version.py
pymoa_remote/client.py
pymoa_remote/exception.py
pymoa_remote/executor.py
pymoa_remote/server.py
pymoa_remote/threading.py
pymoa_remote/utils.py
pymoa_remote/app/__init__.py
pymoa_remote/app/multiprocessing.py
pymoa_remote/app/quart.py
pymoa_remote/rest/__init__.py
pymoa_remote/rest/client.py
pymoa_remote/rest/sse.py
pymoa_remote/socket/__init__.py
pymoa_remote/socket/client.py
pymoa_remote/socket/multiprocessing_client.py
pymoa_remote/socket/websocket_client.py
pymoa_remote/tests/__init__.py
pymoa_remote/tests/conftest.py
pymoa_remote/tests/device.py
pymoa_remote/tests/test_executor.py
pymoa_remote/tests/test_process.py
pymoa_remote/tests/test_quart.py
pymoa_remote/tests/test_threads.py
pymoa_remote-0.1.0.dist-info/licenses/LICENSE
pymoa_remote-0.1.0.dist-info/METADATA
pymoa_remote-0.1.0.dist-info/WHEEL
pymoa_remote-0.1.0.dist-info/entry_points.txt
pymoa_remote-0.1.0.dist-info/top_level.txt
pymoa_remote-0.1.0.dist-info/RECORD
